acme_project_create/__init__.py
acme_project_create/_main.py
acme_project_create/template/template_manifest.py
acme_project_create/template/{{project_name}}/Dockerfile.j2template
acme_project_create/template/{{project_name}}/LICENSE.j2template
acme_project_create/template/{{project_name}}/README.md.j2template
acme_project_create/template/{{project_name}}/compose.yml
acme_project_create/template/{{project_name}}/create_env.sh
acme_project_create/template/{{project_name}}/env.manifest
acme_project_create/template/{{project_name}}/pyproject.toml.j2template
acme_project_create/template/{{project_name}}/run.sh
acme_project_create/template/{{project_name}}/upgrade_env.sh
acme_project_create/template/{{project_name}}/admin/README.md
acme_project_create/template/{{project_name}}/docs/README.md
acme_project_create/template/{{project_name}}/docs/mkdocs.yml.j2template
acme_project_create/template/{{project_name}}/docs/docs/api.md.j2template
acme_project_create/template/{{project_name}}/docs/docs/architecture.md
acme_project_create/template/{{project_name}}/docs/docs/cheat_sheet.md
acme_project_create/template/{{project_name}}/docs/docs/features.md
acme_project_create/template/{{project_name}}/docs/docs/glossary.md
acme_project_create/template/{{project_name}}/docs/docs/guides.md
acme_project_create/template/{{project_name}}/docs/docs/index.md
acme_project_create/template/{{project_name}}/docs/docs/install.md.j2template
acme_project_create/template/{{project_name}}/docs/docs/release_notes.md
acme_project_create/template/{{project_name}}/docs/docs/stylesheets/extra.css
acme_project_create/template/{{project_name}}/src/{{package_name}}/__init__.py
acme_project_create/template/{{project_name}}/src/{{package_name}}/_main.py.j2template
acme_project_create/template/{{project_name}}/tests/{{package_name}}/test_main.py
acme_project_create-0.0.7.dist-info/METADATA
acme_project_create-0.0.7.dist-info/WHEEL
acme_project_create-0.0.7.dist-info/entry_points.txt
acme_project_create-0.0.7.dist-info/top_level.txt
acme_project_create-0.0.7.dist-info/RECORD
