Metadata-Version: 2.2
Name: acme_project_create
Version: 0.0.7
Summary: Sets up a new (python) project using a template
Author-email: guner.stan@gmail.com
License: MIT
Project-URL: homepage, https://blackwhitehere.github.io/acme-project-create
Project-URL: repository, https://github.com/blackwhitehere/acme-project-create
Classifier: Programming Language :: Python :: 3.12
Classifier: Programming Language :: Python :: 3.11
Classifier: Programming Language :: Python :: 3.10
Classifier: Programming Language :: Python :: 3.9
Requires-Python: >=3.9
Requires-Dist: Jinja2
Requires-Dist: python-dotenv
Provides-Extra: dev
Requires-Dist: pytest; extra == "dev"
Requires-Dist: uv; extra == "dev"
Requires-Dist: mkdocs; extra == "dev"
Requires-Dist: mkdocs-material; extra == "dev"
Requires-Dist: mkdocstrings[python]; extra == "dev"
Requires-Dist: jupyterlab; extra == "dev"
Requires-Dist: ruff; extra == "dev"
Requires-Dist: isort; extra == "dev"
Requires-Dist: pre-commit; extra == "dev"
